FoxDotShabda/__init__.py
foxdotshabda-0.1.1.dist-info/METADATA
foxdotshabda-0.1.1.dist-info/WHEEL
foxdotshabda-0.1.1.dist-info/licenses/LICENSE
foxdotshabda-0.1.1.dist-info/RECORD
